setup.py
bin/pystynamic
pystynamic/__init__.py
pystynamic/exceptions.py
pystynamic/generation.py
pystynamic/wsgi_app.py
pystynamic.egg-info/PKG-INFO
pystynamic.egg-info/SOURCES.txt
pystynamic.egg-info/dependency_links.txt
pystynamic.egg-info/top_level.txt
pystynamic/commands/__init__.py
pystynamic/commands/generate.py
pystynamic/commands/serve.py