Metadata-Version: 1.0
Name: pystynamic
Version: 0.12
Summary: Python static website generator
Home-page: http://bitbucket.org/markhildreth/pystynamic
Author: Mark Hildreth
Author-email: mark.k.hildreth@gmail.com
License: UNKNOWN
Platform: UNKNOWN
